lmstudiotxt_generator/__init__.py
lmstudiotxt_generator/analyzer.py
lmstudiotxt_generator/cli.py
lmstudiotxt_generator/config.py
lmstudiotxt_generator/fallback.py
lmstudiotxt_generator/full_builder.py
lmstudiotxt_generator/github.py
lmstudiotxt_generator/lmstudio.py
lmstudiotxt_generator/models.py
lmstudiotxt_generator/pipeline.py
lmstudiotxt_generator/schema.py
lmstudiotxt_generator/signatures.py
lmstudiotxt_generator/.gemini/settings.json
lmstudiotxt_generator/.ruler/AGENTS.md
lmstudio_llmstxt_generator-0.1.1.dist-info/METADATA
lmstudio_llmstxt_generator-0.1.1.dist-info/WHEEL
lmstudio_llmstxt_generator-0.1.1.dist-info/entry_points.txt
lmstudio_llmstxt_generator-0.1.1.dist-info/top_level.txt
lmstudio_llmstxt_generator-0.1.1.dist-info/RECORD
