Metadata-Version: 2.4
Name: lmstudio-llmstxt-generator
Version: 0.1.1
Summary: LM Studio-powered llms.txt generator based on DSPy tutorials.
Requires-Python: >=3.10
Requires-Dist: dspy
Requires-Dist: python-dotenv
Requires-Dist: requests
Requires-Dist: lmstudio
Requires-Dist: llm-ctx
Requires-Dist: llms-txt
Provides-Extra: dev
Requires-Dist: pytest; extra == "dev"
Provides-Extra: test
Requires-Dist: pytest>=8; extra == "test"
